agrajag/__init__.py
agrajag/agrajag.py
agrajag/agrajag_cli.py
agrajag/resources/__init__.py
agrajag-0.1.0.dist-info/LICENSE
agrajag-0.1.0.dist-info/METADATA
agrajag-0.1.0.dist-info/WHEEL
agrajag-0.1.0.dist-info/entry_points.txt
agrajag-0.1.0.dist-info/top_level.txt
agrajag-0.1.0.dist-info/RECORD
